Workbook
Name bl_no_h: INVOICE!$C$13
Name Ocean_vessel_voyage_no: INVOICE!$C$12

Sheet INVOICE
A1: ISSUER:
A2: SKY NICE INTERNATIONAL TRADING LIMITED
A3: ROOMS 1316,13/F,HOLLYWOOD PLAZA,610 NATHAN ROAD,
A4: MONGKOK,KOWLOON,HONG KONG.
A5: TO: | G5: COMMERCIAL INVOICE
A6: CAESAR APPARELS LIMITED
A7: 82,NASIRABAD I/A,
A8: CHATTOGRAM-4209,BANGLADESH.
A9: BIN/VAT REGISTRATION NO.:000319795-0505 | G9: NO. | H9: DWJ251019H | I9: DATE: | J9: 45949
A10: SHIPMENT FROM: | C10: SHANGHAI PORT,CHINA | G10: BB LC NO. | H10: 236025060019 | I10: DATE: | J10: 45944
A11: TO: | C11: CHATTOGRAM,BANGLADESH | G11: ISSUED BY:
A12: VESSEL/VOY NO. | C12: MAERSK BINTULU V.536A | G12: TRUST BANK PLC,CDA AVENUE BRANCH,
A13: B/L NO. | C13: JSSE2516331B | G13: SANMAR TOWER-1(1ST FLOOR),1850/3319,CDA AVENUE,
A14: CONTAINER NO. | C14: TCKU7262512 | G14: EAST NASIRABAD,CHATTOGRAM-4000,BANGLADESH.
A15: SHIPPED ON BOARD: | C15: OCT 19,2025 | G15: BIN NO.000215909-0101.
A16: COMMODITY DESCRIPTION: | D16: FABRICS FOR READY MADE GARMENTS. ORIGIN:CHINA
A17: DELIVERY TERM:CFR CHATTOGRAM,BANGLADESH.(INCOTERMS 2020.)DESCRIPTION OF MERCHANDISE,
A18: QUALITY,QUANTITY,UNIT PRICE AND OTHER SPECIFICATION OF GOODS ARE STRICTLY AS PER BENEFICIARY’S
A19: PROFORMA INVOICE NO.:JSC/PFA/CAL/25159 DATED 16.09.2025 AND SIGNED BETWEEN BUYER AND SELLER.
A20: Shipping Mark | C20: Description of Goods | H20: Quantity(Kgs) | I20: Unit Price | J20: Amount
H21: (CFR CHATTOGRAM,BANGLADESH)
A22: CAESAR APPARELS | C22: 95% RECYCLED POLYESTER 5% ELASTANE AOP KNIT SINGLE JERSEY FABRIC
A23: LTD. | C23: CW:60" WEIGHT:170-180GSM STYLE# 7024625 ORDER NO.103956933
A24: COL. | C24: BLUE FLOWER AOP | H24: 495 | I24: 5.25 | J24: =H24*I24 -> 2598.75
A25: ROLL NO: | B25: QNTY: | C25: GREEN FLOWER AOP | H25: 673 | I25: 5.25 | J25: =H25*I25 -> 3533.25
A26: MADE IN CHINA
C32: TOTAL | H32: =SUM(H24:H31) -> 1168 | J32: =SUM(J24:J31) -> 6132
A33: (INVOICE VALUE: SAY U.S.DOLLARS SIX THOUSAND ONE HUNDRED THIRTY-TWO ONLY.)
A35: FOB VALUE OF THE GOODS: | D35: =J32-J35 -> 5898.4 | H35: FREIGHT CHARGES: | J35: 233.6
A36: WE CERTIFY THAT: | C36: 1)THE MERCHANDISE ARE OF ‘CHINA’ ORIGIN.
C37: 2)THE QUANTITY,QUALITY,UNIT PRICE AND OTHER SPECIFICATION OF THE GOODS
C38: SUPPLIED ARE STRICTLY AS PER BENEFICIARY’S PROFORMA INVOICE NO.:
C39: JSC/PFA/CAL/25159 DATED 16.09.2025 AND SIGNED BETWEEN BUYER AND SELLER.
A41: REFERENCE: | C41: IMPORT UNDER IRC NO.:BA-0164952(OLD),NEW:260315120051220,
C42: TIN NO.:789197699253/CIRCLE-68,H.S.CODE NO.6004.10.00
C43: EXPORT LC NO.ELLOS/CAESAR/001/2025 DATED 01.01.2025
C44: REF:CA-300/TB/DEC-24/EL/AW25/SN 01/PAL/HAS
C45: SHIPMENT UNDER BONDED WAREHOUSE LICENCE.

Sheet PL
A1: =INVOICE!A1 -> ISSUER:
A2: =INVOICE!A2 -> SKY NICE INTERNATIONAL TRADING LIMITED
A3: =INVOICE!A3 -> ROOMS 1316,13/F,HOLLYWOOD PLAZA,610 NATHAN ROAD,
A4: =INVOICE!A4 -> MONGKOK,KOWLOON,HONG KONG.
A5: =INVOICE!A5 -> TO: | G5: DETAILED PACKING LIST
A6: =INVOICE!A6 -> CAESAR APPARELS LIMITED
A7: =INVOICE!A7 -> 82,NASIRABAD I/A,
A8: =INVOICE!A8 -> CHATTOGRAM-4209,BANGLADESH.
A9: =INVOICE!A9 -> BIN/VAT REGISTRATION NO.:000319795-0505 | G9: NO. | H9: =INVOICE!H9 -> DWJ251019H | I9: =INVOICE!I9 -> DATE: | J9: =INVOICE!J9 -> 45949
A10: =INVOICE!A10 -> SHIPMENT FROM: | C10: =INVOICE!C10 -> SHANGHAI PORT,CHINA | G10: =INVOICE!G10 -> BB LC NO. | H10: =INVOICE!H10 -> 236025060019 | I10: =INVOICE!I10 -> DATE: | J10: =INVOICE!J10 -> 45944
A11: =INVOICE!A11 -> TO: | C11: =INVOICE!C11 -> CHATTOGRAM,BANGLADESH | G11: =INVOICE!G11 -> ISSUED BY:
A12: =INVOICE!A12 -> VESSEL/VOY NO. | C12: =INVOICE!C12 -> MAERSK BINTULU V.536A | G12: =INVOICE!G12 -> TRUST BANK PLC,CDA AVENUE BRANCH,
A13: =INVOICE!A13 -> B/L NO. | C13: =INVOICE!C13 -> JSSE2516331B | G13: =INVOICE!G13 -> SANMAR TOWER-1(1ST FLOOR),1850/3319,CDA AVENUE,
A14: =INVOICE!A14 -> CONTAINER NO. | C14: =INVOICE!C14 -> TCKU7262512 | G14: =INVOICE!G14 -> EAST NASIRABAD,CHATTOGRAM-4000,BANGLADESH.
A15: =INVOICE!A15 -> SHIPPED ON BOARD: | C15: =INVOICE!C15 -> OCT 19,2025 | G15: =INVOICE!G15 -> BIN NO.000215909-0101.
A16: =INVOICE!A16 -> COMMODITY DESCRIPTION: | D16: =INVOICE!D16 -> FABRICS FOR READY MADE GARMENTS. ORIGIN:CHINA
A17: =INVOICE!A17 -> DELIVERY TERM:CFR CHATTOGRAM,BANGLADESH.(INCOTERMS 2020.)DESCRIPTION OF MERCHANDISE,
A18: =INVOICE!A18 -> QUALITY,QUANTITY,UNIT PRICE AND OTHER SPECIFICATION OF GOODS ARE STRICTLY AS PER BENEFICIARY’S
A19: =INVOICE!A19 -> PROFORMA INVOICE NO.:JSC/PFA/CAL/25159 DATED 16.09.2025 AND SIGNED BETWEEN BUYER AND SELLER.
A20: =INVOICE!A20 -> Shipping Mark | C20: =INVOICE!C20 -> Description of Goods | G20: Rolls | H20: =INVOICE!H20 -> Quantity(Kgs) | I20: G.W.(kgs) | J20: N.W.(kgs) | K20: CBM
A22: =INVOICE!A22 -> CAESAR APPARELS | C22: =INVOICE!C22 -> 95% RECYCLED POLYESTER 5% ELASTANE AOP KNIT SINGLE JERSEY FABRIC
A23: =INVOICE!A23 -> LTD. | C23: =INVOICE!C23 -> CW:60" WEIGHT:170-180GSM STYLE# 7024625 ORDER NO.103956933
A24: =INVOICE!A24 -> COL. | C24: =INVOICE!C24 -> BLUE FLOWER AOP | G24: 21 | H24: =INVOICE!H24 -> 495 | I24: 505 | J24: 495 | K24: 1.7
A25: =INVOICE!A25 -> ROLL NO: | B25: =INVOICE!B25 -> QNTY: | C25: =INVOICE!C25 -> GREEN FLOWER AOP | G25: 29 | H25: =INVOICE!H25 -> 673 | I25: 688 | J25: 673 | K25: 2.3
A26: =INVOICE!A26 -> MADE IN CHINA
C32: TOTAL | G32: =SUM(G24:G29) -> 50 | H32: =SUM(H24:H29) -> 1168 | I32: =SUM(I24:I29) -> 1193 | J32: =SUM(J24:J29) -> 1168 | K32: =SUM(K24:K31) -> 4
A33: (TOTAL PACKAGES: SAY FIFTY ROLLS ONLY.)
A34: PACKING: | C34: 20YDS UP,STANDARD EXPORT ROLL PACKING.
A36: =INVOICE!A41 -> REFERENCE: | C36: =INVOICE!C41 -> IMPORT UNDER IRC NO.:BA-0164952(OLD),NEW:260315120051220,
C37: =INVOICE!C42 -> TIN NO.:789197699253/CIRCLE-68,H.S.CODE NO.6004.10.00
C38: =INVOICE!C43 -> EXPORT LC NO.ELLOS/CAESAR/001/2025 DATED 01.01.2025
C39: =INVOICE!C44 -> REF:CA-300/TB/DEC-24/EL/AW25/SN 01/PAL/HAS
C40: =INVOICE!C45 -> SHIPMENT UNDER BONDED WAREHOUSE LICENCE.

Sheet WEIGHT
A1: =INVOICE!A1 -> ISSUER:
A2: =INVOICE!A2 -> SKY NICE INTERNATIONAL TRADING LIMITED
A3: =INVOICE!A3 -> ROOMS 1316,13/F,HOLLYWOOD PLAZA,610 NATHAN ROAD,
A4: =INVOICE!A4 -> MONGKOK,KOWLOON,HONG KONG.
A5: =INVOICE!A5 -> TO: | G5: WEIGHT AND MEASUREMENT LIST
A6: =INVOICE!A6 -> CAESAR APPARELS LIMITED
A7: =INVOICE!A7 -> 82,NASIRABAD I/A,
A8: =INVOICE!A8 -> CHATTOGRAM-4209,BANGLADESH.
A9: =INVOICE!A9 -> BIN/VAT REGISTRATION NO.:000319795-0505 | G9: NO. | H9: =INVOICE!H9 -> DWJ251019H | I9: =INVOICE!I9 -> DATE: | J9: =INVOICE!J9 -> 45949
A10: =INVOICE!A10 -> SHIPMENT FROM: | C10: =INVOICE!C10 -> SHANGHAI PORT,CHINA | G10: =INVOICE!G10 -> BB LC NO. | H10: =INVOICE!H10 -> 236025060019 | I10: =INVOICE!I10 -> DATE: | J10: =INVOICE!J10 -> 45944
A11: =INVOICE!A11 -> TO: | C11: =INVOICE!C11 -> CHATTOGRAM,BANGLADESH | G11: =INVOICE!G11 -> ISSUED BY:
A12: =INVOICE!A12 -> VESSEL/VOY NO. | C12: =INVOICE!C12 -> MAERSK BINTULU V.536A | G12: =INVOICE!G12 -> TRUST BANK PLC,CDA AVENUE BRANCH,
A13: =INVOICE!A13 -> B/L NO. | C13: =INVOICE!C13 -> JSSE2516331B | G13: =INVOICE!G13 -> SANMAR TOWER-1(1ST FLOOR),1850/3319,CDA AVENUE,
A14: =INVOICE!A14 -> CONTAINER NO. | C14: =INVOICE!C14 -> TCKU7262512 | G14: =INVOICE!G14 -> EAST NASIRABAD,CHATTOGRAM-4000,BANGLADESH.
A15: =INVOICE!A15 -> SHIPPED ON BOARD: | C15: =INVOICE!C15 -> OCT 19,2025 | G15: =INVOICE!G15 -> BIN NO.000215909-0101.
A16: =INVOICE!A16 -> COMMODITY DESCRIPTION: | D16: =INVOICE!D16 -> FABRICS FOR READY MADE GARMENTS. ORIGIN:CHINA
A17: =INVOICE!A17 -> DELIVERY TERM:CFR CHATTOGRAM,BANGLADESH.(INCOTERMS 2020.)DESCRIPTION OF MERCHANDISE,
A18: =INVOICE!A18 -> QUALITY,QUANTITY,UNIT PRICE AND OTHER SPECIFICATION OF GOODS ARE STRICTLY AS PER BENEFICIARY’S
A19: =INVOICE!A19 -> PROFORMA INVOICE NO.:JSC/PFA/CAL/25159 DATED 16.09.2025 AND SIGNED BETWEEN BUYER AND SELLER.
A20: =INVOICE!A20 -> Shipping Mark | C20: =INVOICE!C20 -> Description of Goods | G20: Rolls | H20: =INVOICE!H20 -> Quantity(Kgs) | I20: G.W.(kgs) | J20: N.W.(kgs) | K20: CBM
A22: =INVOICE!A22 -> CAESAR APPARELS | C22: =INVOICE!C22 -> 95% RECYCLED POLYESTER 5% ELASTANE AOP KNIT SINGLE JERSEY FABRIC
A23: =INVOICE!A23 -> LTD. | C23: =INVOICE!C23 -> CW:60" WEIGHT:170-180GSM STYLE# 7024625 ORDER NO.103956933
A24: =INVOICE!A24 -> COL. | C24: =INVOICE!C24 -> BLUE FLOWER AOP | G24: =PL!G24 -> 21 | H24: =PL!H24 -> 495 | I24: =PL!I24 -> 505 | J24: =PL!J24 -> 495 | K24: =PL!K24 -> 1.7
A25: =INVOICE!A25 -> ROLL NO: | B25: =INVOICE!B25 -> QNTY: | C25: =INVOICE!C25 -> GREEN FLOWER AOP | G25: =PL!G25 -> 29 | H25: =PL!H25 -> 673 | I25: =PL!I25 -> 688 | J25: =PL!J25 -> 673 | K25: =PL!K25 -> 2.3
A26: =INVOICE!A26 -> MADE IN CHINA
C31: TOTAL | G31: =SUM(G24:G29) -> 50 | H31: =PL!H32 -> 1168 | I31: =PL!I32 -> 1193 | J31: =PL!J32 -> 1168 | K31: =PL!K32 -> 4
A33: =INVOICE!A41 -> REFERENCE: | C33: =INVOICE!C41 -> IMPORT UNDER IRC NO.:BA-0164952(OLD),NEW:260315120051220,
C34: =INVOICE!C42 -> TIN NO.:789197699253/CIRCLE-68,H.S.CODE NO.6004.10.00
C35: =INVOICE!C43 -> EXPORT LC NO.ELLOS/CAESAR/001/2025 DATED 01.01.2025
C36: =INVOICE!C44 -> REF:CA-300/TB/DEC-24/EL/AW25/SN 01/PAL/HAS
C37: =INVOICE!C45 -> SHIPMENT UNDER BONDED WAREHOUSE LICENCE.

Sheet PRE SHIPMENT
A1: =INVOICE!A1 -> ISSUER:
A2: =INVOICE!A2 -> SKY NICE INTERNATIONAL TRADING LIMITED
A3: =INVOICE!A3 -> ROOMS 1316,13/F,HOLLYWOOD PLAZA,610 NATHAN ROAD,
A4: =INVOICE!A4 -> MONGKOK,KOWLOON,HONG KONG.
A5: =INVOICE!A5 -> TO: | G5: PRE-SHIPMENT INSPECTION CERTIFICATE
A6: =INVOICE!A6 -> CAESAR APPARELS LIMITED
A7: =INVOICE!A7 -> 82,NASIRABAD I/A,
A8: =INVOICE!A8 -> CHATTOGRAM-4209,BANGLADESH.
A9: =INVOICE!A9 -> BIN/VAT REGISTRATION NO.:000319795-0505 | G9: NO. | H9: =INVOICE!H9 -> DWJ251019H | I9: =INVOICE!I9 -> DATE: | J9: =INVOICE!J9 -> 45949
A10: =INVOICE!A10 -> SHIPMENT FROM: | C10: =INVOICE!C10 -> SHANGHAI PORT,CHINA | G10: =INVOICE!G10 -> BB LC NO. | H10: =INVOICE!H10 -> 236025060019 | I10: =INVOICE!I10 -> DATE: | J10: =INVOICE!J10 -> 45944
A11: =INVOICE!A11 -> TO: | C11: =INVOICE!C11 -> CHATTOGRAM,BANGLADESH | G11: =INVOICE!G11 -> ISSUED BY:
A12: =INVOICE!A12 -> VESSEL/VOY NO. | C12: =INVOICE!C12 -> MAERSK BINTULU V.536A | G12: =INVOICE!G12 -> TRUST BANK PLC,CDA AVENUE BRANCH,
A13: =INVOICE!A13 -> B/L NO. | C13: =INVOICE!C13 -> JSSE2516331B | G13: =INVOICE!G13 -> SANMAR TOWER-1(1ST FLOOR),1850/3319,CDA AVENUE,
A14: =INVOICE!A14 -> CONTAINER NO. | C14: =INVOICE!C14 -> TCKU7262512 | G14: =INVOICE!G14 -> EAST NASIRABAD,CHATTOGRAM-4000,BANGLADESH.
A15: =INVOICE!A15 -> SHIPPED ON BOARD: | C15: =INVOICE!C15 -> OCT 19,2025 | G15: =INVOICE!G15 -> BIN NO.000215909-0101.
A16: =INVOICE!A16 -> COMMODITY DESCRIPTION:
A17: WE,AS INSPECTOR, HEREBY CERTIFY THAT WE HAVE CARRIED OUT 100PCT CONSIGNMENT INSPECTION
A18: AT OUR COST BEFROE SHIPMENT AS BELOW:
A19: FABRICS FOR READYMADE GARMENTS ORIGIN:CHINA
A20: =INVOICE!A20 -> Shipping Mark | C20: =INVOICE!C20 -> Description of Goods | G20: Rolls | H20: =PL!H20 -> Quantity(Kgs) | I20: =PL!I20 -> G.W.(kgs) | J20: N.W.(kgs) | K20: CBM
A22: =INVOICE!A22 -> CAESAR APPARELS | C22: =INVOICE!C22 -> 95% RECYCLED POLYESTER 5% ELASTANE AOP KNIT SINGLE JERSEY FABRIC
A23: =INVOICE!A23 -> LTD. | C23: =INVOICE!C23 -> CW:60" WEIGHT:170-180GSM STYLE# 7024625 ORDER NO.103956933
A24: =INVOICE!A24 -> COL. | C24: =INVOICE!C24 -> BLUE FLOWER AOP | G24: =PL!G24 -> 21 | H24: =PL!H24 -> 495 | I24: =PL!I24 -> 505 | J24: =PL!J24 -> 495 | K24: =PL!K24 -> 1.7
A25: =INVOICE!A25 -> ROLL NO: | B25: =INVOICE!B25 -> QNTY: | C25: =INVOICE!C25 -> GREEN FLOWER AOP | G25: =PL!G25 -> 29 | H25: =PL!H25 -> 673 | I25: =PL!I25 -> 688 | J25: =PL!J25 -> 673 | K25: =PL!K25 -> 2.3
A26: =INVOICE!A26 -> MADE IN CHINA
C32: TOTAL | G32: =PL!G32 -> 50 | H32: =PL!H32 -> 1168 | I32: =PL!I32 -> 1193 | J32: =PL!J32 -> 1168 | K32: =PL!K32 -> 4
A33: PACKING: | C33: =PL!C34 -> 20YDS UP,STANDARD EXPORT ROLL PACKING.
A34: INVOICE VALUE: | C34: =INVOICE!J32 -> 6132 | D34: =INVOICE!H21 -> (CFR CHATTOGRAM,BANGLADESH)
A35: RESULTS: | C35: REGARDING QUANTITY ,QUALITY, INVOICE VALUE,UNIT PRICE,ETC. ARE CONFORM TO
C36: LC NO.236025060019 AND BENEFICIARY’S PROFORMA INVOICE NO.:
C37: JSC/PFA/CAL/25159 DATED 16.09.2025 AND SIGNED BETWEEN BUYER AND SELLER.
A39: =INVOICE!A41 -> REFERENCE: | C39: =INVOICE!C41 -> IMPORT UNDER IRC NO.:BA-0164952(OLD),NEW:260315120051220,
C40: =INVOICE!C42 -> TIN NO.:789197699253/CIRCLE-68,H.S.CODE NO.6004.10.00
C41: =INVOICE!C43 -> EXPORT LC NO.ELLOS/CAESAR/001/2025 DATED 01.01.2025
C42: =INVOICE!C44 -> REF:CA-300/TB/DEC-24/EL/AW25/SN 01/PAL/HAS
C43: =INVOICE!C45 -> SHIPMENT UNDER BONDED WAREHOUSE LICENCE.
